{
  "directed": false,
  "multigraph": false,
  "graph": {
    "hyperedges": [
      {
        "id": "conversion_artifact_closed_loop",
        "label": "Conversion Artifact Closed Loop",
        "nodes": [
          "service_conversion_service",
          "service_s3_storage",
          "service_bim_control",
          "service_review_coordinator",
          "service_web_viewer",
          "service_bim_streaming_server"
        ],
        "relation": "participate_in",
        "confidence": "INFERRED",
        "confidence_score": 0.9,
        "source_file": "plans/IFC_TO_USDC_CONVERSION_API_IMPLEMENTATION_PLAN.md"
      },
      {
        "id": "review_highlight_runtime_loop",
        "label": "Review Issue to 3D Runtime Loop",
        "nodes": [
          "data_review_issue",
          "data_element_mapping",
          "data_usd_prim_path",
          "dc_highlight_prims_request",
          "service_bim_streaming_server",
          "socket_highlight_request"
        ],
        "relation": "form",
        "confidence": "INFERRED",
        "confidence_score": 0.88,
        "source_file": "plans/BIM_REVIEW_COORDINATOR_WEB_VIEWER_EXECUTION_PLAN.md"
      },
      {
        "id": "single_repo_operational_context",
        "label": "Single Repo Operational Context",
        "nodes": [
          "repo_ai_bim_governance",
          "doc_nested_repo_remote_record",
          "doc_local_runbook",
          "doc_ifc_usdc_plan",
          "doc_review_web_plan"
        ],
        "relation": "form",
        "confidence": "INFERRED",
        "confidence_score": 0.82,
        "source_file": "git/nested-repo-remotes.md"
      }
    ]
  },
  "nodes": [
    {
      "label": "BIM Review Coordinator + Web Viewer Execution Plan",
      "file_type": "document",
      "source_file": "plans/BIM_REVIEW_COORDINATOR_WEB_VIEWER_EXECUTION_PLAN.md",
      "source_location": "line 1",
      "source_url": null,
      "captured_at": null,
      "author": null,
      "contributor": null,
      "id": "doc_review_web_plan",
      "community": 6,
      "norm_label": "bim review coordinator + web viewer execution plan"
    },
    {
      "label": "IFC to USDC Conversion API Plan",
      "file_type": "document",
      "source_file": "plans/IFC_TO_USDC_CONVERSION_API_IMPLEMENTATION_PLAN.md",
      "source_location": "line 1",
      "source_url": null,
      "captured_at": null,
      "author": null,
      "contributor": null,
      "id": "doc_ifc_usdc_plan",
      "community": 0,
      "norm_label": "ifc to usdc conversion api plan"
    },
    {
      "label": "Review Session API Contract",
      "file_type": "document",
      "source_file": "contracts/review-session-api.md",
      "source_location": "line 1",
      "source_url": null,
      "captured_at": null,
      "author": null,
      "contributor": null,
      "id": "doc_review_session_api",
      "community": 5,
      "norm_label": "review session api contract"
    },
    {
      "label": "Streaming DataChannel Events Contract",
      "file_type": "document",
      "source_file": "contracts/streaming-datachannel-events.md",
      "source_location": "line 1",
      "source_url": null,
      "captured_at": null,
      "author": null,
      "contributor": null,
      "id": "doc_datachannel_contract",
      "community": 0,
      "norm_label": "streaming datachannel events contract"
    },
    {
      "label": "Coordinator Socket Events Contract",
      "file_type": "document",
      "source_file": "contracts/coordinator-socket-events.md",
      "source_location": "line 1",
      "source_url": null,
      "captured_at": null,
      "author": null,
      "contributor": null,
      "id": "doc_socket_contract",
      "community": 6,
      "norm_label": "coordinator socket events contract"
    },
    {
      "label": "IFC to USDC Conversion API Contract",
      "file_type": "document",
      "source_file": "contracts/conversion-api.md",
      "source_location": "line 1",
      "source_url": null,
      "captured_at": null,
      "author": null,
      "contributor": null,
      "id": "doc_conversion_api",
      "community": 5,
      "norm_label": "ifc to usdc conversion api contract"
    },
    {
      "label": "Fake BIM Control API Contract",
      "file_type": "document",
      "source_file": "contracts/bim-control-fake-api.md",
      "source_location": "line 1",
      "source_url": null,
      "captured_at": null,
      "author": null,
      "contributor": null,
      "id": "doc_bim_control_api",
      "community": 1,
      "norm_label": "fake bim control api contract"
    },
    {
      "label": "Local Development Runbook",
      "file_type": "document",
      "source_file": "contracts/local-dev-runbook.md",
      "source_location": "line 1",
      "source_url": null,
      "captured_at": null,
      "author": null,
      "contributor": null,
      "id": "doc_local_runbook",
      "community": 2,
      "norm_label": "local development runbook"
    },
    {
      "label": "Nested Repo Remote Record",
      "file_type": "document",
      "source_file": "git/nested-repo-remotes.md",
      "source_location": "line 1",
      "source_url": null,
      "captured_at": null,
      "author": null,
      "contributor": null,
      "id": "doc_nested_repo_remote_record",
      "community": 2,
      "norm_label": "nested repo remote record"
    },
    {
      "label": "AI-BIM-governance Single Root Repo",
      "file_type": "document",
      "source_file": "git/nested-repo-remotes.md",
      "source_location": "Root Repo",
      "source_url": null,
      "captured_at": null,
      "author": null,
      "contributor": null,
      "id": "repo_ai_bim_governance",
      "community": 2,
      "norm_label": "ai-bim-governance single root repo"
    },
    {
      "label": "_conversion-service",
      "file_type": "document",
      "source_file": "plans/IFC_TO_USDC_CONVERSION_API_IMPLEMENTATION_PLAN.md",
      "source_location": "section 1.1",
      "source_url": null,
      "captured_at": null,
      "author": null,
      "contributor": null,
      "id": "service_conversion_service",
      "community": 5,
      "norm_label": "_conversion-service"
    },
    {
      "label": "bim-streaming-server",
      "file_type": "document",
      "source_file": "plans/IFC_TO_USDC_CONVERSION_API_IMPLEMENTATION_PLAN.md",
      "source_location": "section 1.2",
      "source_url": null,
      "captured_at": null,
      "author": null,
      "contributor": null,
      "id": "service_bim_streaming_server",
      "community": 0,
      "norm_label": "bim-streaming-server"
    },
    {
      "label": "_s3_storage",
      "file_type": "document",
      "source_file": "plans/IFC_TO_USDC_CONVERSION_API_IMPLEMENTATION_PLAN.md",
      "source_location": "section 1.3",
      "source_url": null,
      "captured_at": null,
      "author": null,
      "contributor": null,
      "id": "service_s3_storage",
      "community": 1,
      "norm_label": "_s3_storage"
    },
    {
      "label": "_bim-control",
      "file_type": "document",
      "source_file": "plans/IFC_TO_USDC_CONVERSION_API_IMPLEMENTATION_PLAN.md",
      "source_location": "section 1.4",
      "source_url": null,
      "captured_at": null,
      "author": null,
      "contributor": null,
      "id": "service_bim_control",
      "community": 1,
      "norm_label": "_bim-control"
    },
    {
      "label": "web-viewer-sample",
      "file_type": "document",
      "source_file": "plans/IFC_TO_USDC_CONVERSION_API_IMPLEMENTATION_PLAN.md",
      "source_location": "section 1.5",
      "source_url": null,
      "captured_at": null,
      "author": null,
      "contributor": null,
      "id": "service_web_viewer",
      "community": 0,
      "norm_label": "web-viewer-sample"
    },
    {
      "label": "bim-review-coordinator",
      "file_type": "document",
      "source_file": "plans/BIM_REVIEW_COORDINATOR_WEB_VIEWER_EXECUTION_PLAN.md",
      "source_location": "section 1.1",
      "source_url": null,
      "captured_at": null,
      "author": null,
      "contributor": null,
      "id": "service_review_coordinator",
      "community": 4,
      "norm_label": "bim-review-coordinator"
    },
    {
      "label": "Absorbed bim-streaming-server Repo",
      "file_type": "document",
      "source_file": "git/nested-repo-remotes.md",
      "source_location": "Absorbed Repos",
      "source_url": null,
      "captured_at": null,
      "author": null,
      "contributor": null,
      "id": "repo_absorbed_bim_streaming",
      "community": 2,
      "norm_label": "absorbed bim-streaming-server repo"
    },
    {
      "label": "Absorbed web-viewer-sample Repo",
      "file_type": "document",
      "source_file": "git/nested-repo-remotes.md",
      "source_location": "Absorbed Repos",
      "source_url": null,
      "captured_at": null,
      "author": null,
      "contributor": null,
      "id": "repo_absorbed_web_viewer",
      "community": 2,
      "norm_label": "absorbed web-viewer-sample repo"
    },
    {
      "label": "GitHub Root Remote monkey1sai/AI-BIM-governance",
      "file_type": "document",
      "source_file": "git/nested-repo-remotes.md",
      "source_location": "Root Repo",
      "source_url": null,
      "captured_at": null,
      "author": null,
      "contributor": null,
      "id": "git_root_remote",
      "community": 2,
      "norm_label": "github root remote monkey1sai/ai-bim-governance"
    },
    {
      "label": "Nested .git Backup Outside Workspace",
      "file_type": "document",
      "source_file": "git/nested-git-backup-path.txt",
      "source_location": "line 1",
      "source_url": null,
      "captured_at": null,
      "author": null,
      "contributor": null,
      "id": "git_nested_backup",
      "community": 2,
      "norm_label": "nested .git backup outside workspace"
    },
    {
      "label": "IFC Source File",
      "file_type": "document",
      "source_file": "contracts/conversion-api.md",
      "source_location": "Create Conversion",
      "source_url": null,
      "captured_at": null,
      "author": null,
      "contributor": null,
      "id": "data_ifc_file",
      "community": 3,
      "norm_label": "ifc source file"
    },
    {
      "label": "USDC Runtime Model",
      "file_type": "document",
      "source_file": "contracts/conversion-api.md",
      "source_location": "Successful jobs publish",
      "source_url": null,
      "captured_at": null,
      "author": null,
      "contributor": null,
      "id": "data_usdc_model",
      "community": 0,
      "norm_label": "usdc runtime model"
    },
    {
      "label": "ifc_index.json",
      "file_type": "document",
      "source_file": "contracts/conversion-api.md",
      "source_location": "Successful jobs publish",
      "source_url": null,
      "captured_at": null,
      "author": null,
      "contributor": null,
      "id": "data_ifc_index",
      "community": 3,
      "norm_label": "ifc_index.json"
    },
    {
      "label": "usd_index.json",
      "file_type": "document",
      "source_file": "contracts/conversion-api.md",
      "source_location": "Successful jobs publish",
      "source_url": null,
      "captured_at": null,
      "author": null,
      "contributor": null,
      "id": "data_usd_index",
      "community": 3,
      "norm_label": "usd_index.json"
    },
    {
      "label": "element_mapping.json",
      "file_type": "document",
      "source_file": "contracts/conversion-api.md",
      "source_location": "Successful jobs publish",
      "source_url": null,
      "captured_at": null,
      "author": null,
      "contributor": null,
      "id": "data_element_mapping",
      "community": 3,
      "norm_label": "element_mapping.json"
    },
    {
      "label": "IFC GlobalId / GUID",
      "file_type": "document",
      "source_file": "plans/IFC_TO_USDC_CONVERSION_API_IMPLEMENTATION_PLAN.md",
      "source_location": "section 10.3",
      "source_url": null,
      "captured_at": null,
      "author": null,
      "contributor": null,
      "id": "data_ifc_guid",
      "community": 3,
      "norm_label": "ifc globalid / guid"
    },
    {
      "label": "USD Prim Path",
      "file_type": "document",
      "source_file": "contracts/streaming-datachannel-events.md",
      "source_location": "Highlight Prims",
      "source_url": null,
      "captured_at": null,
      "author": null,
      "contributor": null,
      "id": "data_usd_prim_path",
      "community": 3,
      "norm_label": "usd prim path"
    },
    {
      "label": "Artifact Metadata",
      "file_type": "document",
      "source_file": "contracts/bim-control-fake-api.md",
      "source_location": "Endpoints",
      "source_url": null,
      "captured_at": null,
      "author": null,
      "contributor": null,
      "id": "data_artifact_metadata",
      "community": 1,
      "norm_label": "artifact metadata"
    },
    {
      "label": "Review Issue Metadata",
      "file_type": "document",
      "source_file": "contracts/bim-control-fake-api.md",
      "source_location": "Endpoints",
      "source_url": null,
      "captured_at": null,
      "author": null,
      "contributor": null,
      "id": "data_review_issue",
      "community": 6,
      "norm_label": "review issue metadata"
    },
    {
      "label": "Annotation Metadata",
      "file_type": "document",
      "source_file": "contracts/bim-control-fake-api.md",
      "source_location": "Endpoints",
      "source_url": null,
      "captured_at": null,
      "author": null,
      "contributor": null,
      "id": "data_annotation",
      "community": 1,
      "norm_label": "annotation metadata"
    },
    {
      "label": "Review Session State",
      "file_type": "document",
      "source_file": "contracts/review-session-api.md",
      "source_location": "Endpoints",
      "source_url": null,
      "captured_at": null,
      "author": null,
      "contributor": null,
      "id": "data_review_session",
      "community": 4,
      "norm_label": "review session state"
    },
    {
      "label": "WebRTC Stream Config",
      "file_type": "document",
      "source_file": "contracts/review-session-api.md",
      "source_location": "Stream Config",
      "source_url": null,
      "captured_at": null,
      "author": null,
      "contributor": null,
      "id": "data_stream_config",
      "community": 4,
      "norm_label": "webrtc stream config"
    },
    {
      "label": "Conversion Job",
      "file_type": "document",
      "source_file": "contracts/conversion-api.md",
      "source_location": "Create Conversion",
      "source_url": null,
      "captured_at": null,
      "author": null,
      "contributor": null,
      "id": "data_conversion_job",
      "community": 3,
      "norm_label": "conversion job"
    },
    {
      "label": "Conversion Result",
      "file_type": "document",
      "source_file": "contracts/conversion-api.md",
      "source_location": "result",
      "source_url": null,
      "captured_at": null,
      "author": null,
      "contributor": null,
      "id": "data_conversion_result",
      "community": 1,
      "norm_label": "conversion result"
    },
    {
      "label": "Mapping Summary",
      "file_type": "document",
      "source_file": "plans/IFC_TO_USDC_CONVERSION_API_IMPLEMENTATION_PLAN.md",
      "source_location": "section 11.4",
      "source_url": null,
      "captured_at": null,
      "author": null,
      "contributor": null,
      "id": "data_mapping_summary",
      "community": 3,
      "norm_label": "mapping summary"
    },
    {
      "label": "POST /api/conversions",
      "file_type": "document",
      "source_file": "contracts/conversion-api.md",
      "source_location": "Endpoints",
      "source_url": null,
      "captured_at": null,
      "author": null,
      "contributor": null,
      "id": "api_post_conversions",
      "community": 5,
      "norm_label": "post /api/conversions"
    },
    {
      "label": "GET /api/conversions/{job_id}/result",
      "file_type": "document",
      "source_file": "contracts/conversion-api.md",
      "source_location": "Endpoints",
      "source_url": null,
      "captured_at": null,
      "author": null,
      "contributor": null,
      "id": "api_get_conversion_result",
      "community": 5,
      "norm_label": "get /api/conversions/{job_id}/result"
    },
    {
      "label": "POST /api/model-versions/{model_version_id}/conversion-result",
      "file_type": "document",
      "source_file": "contracts/bim-control-fake-api.md",
      "source_location": "Endpoints",
      "source_url": null,
      "captured_at": null,
      "author": null,
      "contributor": null,
      "id": "api_post_conversion_result",
      "community": 1,
      "norm_label": "post /api/model-versions/{model_version_id}/conversion-result"
    },
    {
      "label": "GET /api/model-versions/{model_version_id}/artifacts",
      "file_type": "document",
      "source_file": "contracts/bim-control-fake-api.md",
      "source_location": "Endpoints",
      "source_url": null,
      "captured_at": null,
      "author": null,
      "contributor": null,
      "id": "api_get_artifacts",
      "community": 1,
      "norm_label": "get /api/model-versions/{model_version_id}/artifacts"
    },
    {
      "label": "GET /api/model-versions/{model_version_id}/review-issues",
      "file_type": "document",
      "source_file": "contracts/bim-control-fake-api.md",
      "source_location": "Endpoints",
      "source_url": null,
      "captured_at": null,
      "author": null,
      "contributor": null,
      "id": "api_get_review_issues",
      "community": 6,
      "norm_label": "get /api/model-versions/{model_version_id}/review-issues"
    },
    {
      "label": "POST /api/review-sessions/{session_id}/annotations",
      "file_type": "document",
      "source_file": "contracts/bim-control-fake-api.md",
      "source_location": "Endpoints",
      "source_url": null,
      "captured_at": null,
      "author": null,
      "contributor": null,
      "id": "api_post_annotations",
      "community": 1,
      "norm_label": "post /api/review-sessions/{session_id}/annotations"
    },
    {
      "label": "POST /api/review-sessions",
      "file_type": "document",
      "source_file": "contracts/review-session-api.md",
      "source_location": "Endpoints",
      "source_url": null,
      "captured_at": null,
      "author": null,
      "contributor": null,
      "id": "api_post_review_sessions",
      "community": 4,
      "norm_label": "post /api/review-sessions"
    },
    {
      "label": "GET /api/review-sessions/{session_id}/stream-config",
      "file_type": "document",
      "source_file": "contracts/review-session-api.md",
      "source_location": "Endpoints",
      "source_url": null,
      "captured_at": null,
      "author": null,
      "contributor": null,
      "id": "api_get_stream_config",
      "community": 4,
      "norm_label": "get /api/review-sessions/{session_id}/stream-config"
    },
    {
      "label": "GET /api/model-versions/{model_version_id}/review-bootstrap",
      "file_type": "document",
      "source_file": "contracts/review-session-api.md",
      "source_location": "Endpoints",
      "source_url": null,
      "captured_at": null,
      "author": null,
      "contributor": null,
      "id": "api_get_review_bootstrap",
      "community": 4,
      "norm_label": "get /api/model-versions/{model_version_id}/review-bootstrap"
    },
    {
      "label": "Socket.IO joinSession",
      "file_type": "document",
      "source_file": "contracts/coordinator-socket-events.md",
      "source_location": "Client To Coordinator",
      "source_url": null,
      "captured_at": null,
      "author": null,
      "contributor": null,
      "id": "socket_join_session",
      "community": 4,
      "norm_label": "socket.io joinsession"
    },
    {
      "label": "Socket.IO highlightRequest",
      "file_type": "document",
      "source_file": "contracts/coordinator-socket-events.md",
      "source_location": "Client To Coordinator",
      "source_url": null,
      "captured_at": null,
      "author": null,
      "contributor": null,
      "id": "socket_highlight_request",
      "community": 6,
      "norm_label": "socket.io highlightrequest"
    },
    {
      "label": "Socket.IO selectionUpdate",
      "file_type": "document",
      "source_file": "contracts/coordinator-socket-events.md",
      "source_location": "Client To Coordinator",
      "source_url": null,
      "captured_at": null,
      "author": null,
      "contributor": null,
      "id": "socket_selection_update",
      "community": 3,
      "norm_label": "socket.io selectionupdate"
    },
    {
      "label": "Socket.IO annotationCreate",
      "file_type": "document",
      "source_file": "contracts/coordinator-socket-events.md",
      "source_location": "Client To Coordinator",
      "source_url": null,
      "captured_at": null,
      "author": null,
      "contributor": null,
      "id": "socket_annotation_create",
      "community": 1,
      "norm_label": "socket.io annotationcreate"
    },
    {
      "label": "Socket.IO presenceUpdated",
      "file_type": "document",
      "source_file": "contracts/coordinator-socket-events.md",
      "source_location": "Coordinator To Clients",
      "source_url": null,
      "captured_at": null,
      "author": null,
      "contributor": null,
      "id": "socket_presence_updated",
      "community": 4,
      "norm_label": "socket.io presenceupdated"
    },
    {
      "label": "DataChannel openStageRequest",
      "file_type": "document",
      "source_file": "contracts/streaming-datachannel-events.md",
      "source_location": "Open Stage",
      "source_url": null,
      "captured_at": null,
      "author": null,
      "contributor": null,
      "id": "dc_open_stage_request",
      "community": 0,
      "norm_label": "datachannel openstagerequest"
    },
    {
      "label": "DataChannel openedStageResult",
      "file_type": "document",
      "source_file": "contracts/streaming-datachannel-events.md",
      "source_location": "Open Stage",
      "source_url": null,
      "captured_at": null,
      "author": null,
      "contributor": null,
      "id": "dc_opened_stage_result",
      "community": 0,
      "norm_label": "datachannel openedstageresult"
    },
    {
      "label": "DataChannel highlightPrimsRequest",
      "file_type": "document",
      "source_file": "contracts/streaming-datachannel-events.md",
      "source_location": "Highlight Prims",
      "source_url": null,
      "captured_at": null,
      "author": null,
      "contributor": null,
      "id": "dc_highlight_prims_request",
      "community": 0,
      "norm_label": "datachannel highlightprimsrequest"
    },
    {
      "label": "DataChannel highlightPrimsResult",
      "file_type": "document",
      "source_file": "contracts/streaming-datachannel-events.md",
      "source_location": "Highlight Prims",
      "source_url": null,
      "captured_at": null,
      "author": null,
      "contributor": null,
      "id": "dc_highlight_prims_result",
      "community": 0,
      "norm_label": "datachannel highlightprimsresult"
    },
    {
      "label": "DataChannel clearHighlightRequest",
      "file_type": "document",
      "source_file": "plans/BIM_REVIEW_COORDINATOR_WEB_VIEWER_EXECUTION_PLAN.md",
      "source_location": "section 9.5",
      "source_url": null,
      "captured_at": null,
      "author": null,
      "contributor": null,
      "id": "dc_clear_highlight_request",
      "community": 0,
      "norm_label": "datachannel clearhighlightrequest"
    },
    {
      "label": "DataChannel focusPrimRequest",
      "file_type": "document",
      "source_file": "plans/BIM_REVIEW_COORDINATOR_WEB_VIEWER_EXECUTION_PLAN.md",
      "source_location": "section 9.6",
      "source_url": null,
      "captured_at": null,
      "author": null,
      "contributor": null,
      "id": "dc_focus_prim_request",
      "community": 3,
      "norm_label": "datachannel focusprimrequest"
    },
    {
      "label": "Conversion Publish Flow",
      "file_type": "document",
      "source_file": "plans/IFC_TO_USDC_CONVERSION_API_IMPLEMENTATION_PLAN.md",
      "source_location": "section 12",
      "source_url": null,
      "captured_at": null,
      "author": null,
      "contributor": null,
      "id": "flow_conversion_publish",
      "community": 5,
      "norm_label": "conversion publish flow"
    },
    {
      "label": "Artifact Discovery Flow",
      "file_type": "document",
      "source_file": "plans/BIM_REVIEW_COORDINATOR_WEB_VIEWER_EXECUTION_PLAN.md",
      "source_location": "section 2",
      "source_url": null,
      "captured_at": null,
      "author": null,
      "contributor": null,
      "id": "flow_artifact_discovery",
      "community": 1,
      "norm_label": "artifact discovery flow"
    },
    {
      "label": "Review Session Bootstrap Flow",
      "file_type": "document",
      "source_file": "plans/BIM_REVIEW_COORDINATOR_WEB_VIEWER_EXECUTION_PLAN.md",
      "source_location": "section 10.4",
      "source_url": null,
      "captured_at": null,
      "author": null,
      "contributor": null,
      "id": "flow_review_session_bootstrap",
      "community": 4,
      "norm_label": "review session bootstrap flow"
    },
    {
      "label": "Streaming Open Stage Flow",
      "file_type": "document",
      "source_file": "plans/BIM_REVIEW_COORDINATOR_WEB_VIEWER_EXECUTION_PLAN.md",
      "source_location": "section 9",
      "source_url": null,
      "captured_at": null,
      "author": null,
      "contributor": null,
      "id": "flow_streaming_open_stage",
      "community": 0,
      "norm_label": "streaming open stage flow"
    },
    {
      "label": "Issue to 3D Highlight Flow",
      "file_type": "document",
      "source_file": "plans/BIM_REVIEW_COORDINATOR_WEB_VIEWER_EXECUTION_PLAN.md",
      "source_location": "section 18",
      "source_url": null,
      "captured_at": null,
      "author": null,
      "contributor": null,
      "id": "flow_issue_highlight",
      "community": 6,
      "norm_label": "issue to 3d highlight flow"
    },
    {
      "label": "Annotation Persistence Flow",
      "file_type": "document",
      "source_file": "contracts/coordinator-socket-events.md",
      "source_location": "annotationCreate",
      "source_url": null,
      "captured_at": null,
      "author": null,
      "contributor": null,
      "id": "flow_annotation_persist",
      "community": 1,
      "norm_label": "annotation persistence flow"
    },
    {
      "label": "Local Service Startup Sequence",
      "file_type": "document",
      "source_file": "contracts/local-dev-runbook.md",
      "source_location": "sections 1-6",
      "source_url": null,
      "captured_at": null,
      "author": null,
      "contributor": null,
      "id": "flow_local_run_sequence",
      "community": 2,
      "norm_label": "local service startup sequence"
    },
    {
      "label": "Real Browser DataChannel Validation",
      "file_type": "document",
      "source_file": "plans/IFC_TO_USDC_CONVERSION_API_IMPLEMENTATION_PLAN.md",
      "source_location": "Final Acceptance",
      "source_url": null,
      "captured_at": null,
      "author": null,
      "contributor": null,
      "id": "flow_e2e_browser_validation",
      "community": 0,
      "norm_label": "real browser datachannel validation"
    },
    {
      "label": "Metadata and File Bytes Stay Separate",
      "file_type": "document",
      "source_file": "contracts/bim-control-fake-api.md",
      "source_location": "intro",
      "source_url": null,
      "captured_at": null,
      "author": null,
      "contributor": null,
      "id": "rule_metadata_vs_bytes",
      "community": 1,
      "norm_label": "metadata and file bytes stay separate"
    },
    {
      "label": "Conversion Service Pluggable Not Rewritten",
      "file_type": "document",
      "source_file": "plans/BIM_REVIEW_COORDINATOR_WEB_VIEWER_EXECUTION_PLAN.md",
      "source_location": "section 18",
      "source_url": null,
      "captured_at": null,
      "author": null,
      "contributor": null,
      "id": "rule_conversion_service_pluggable",
      "community": 5,
      "norm_label": "conversion service pluggable not rewritten"
    },
    {
      "label": "Missing USDC Blocks openStageRequest",
      "file_type": "document",
      "source_file": "plans/BIM_REVIEW_COORDINATOR_WEB_VIEWER_EXECUTION_PLAN.md",
      "source_location": "section 17.1",
      "source_url": null,
      "captured_at": null,
      "author": null,
      "contributor": null,
      "id": "rule_missing_usdc_gate",
      "community": 0,
      "norm_label": "missing usdc blocks openstagerequest"
    },
    {
      "label": "Highlight Uses Selection Fallback",
      "file_type": "document",
      "source_file": "contracts/streaming-datachannel-events.md",
      "source_location": "Highlight Prims",
      "source_url": null,
      "captured_at": null,
      "author": null,
      "contributor": null,
      "id": "rule_highlight_fallback",
      "community": 0,
      "norm_label": "highlight uses selection fallback"
    },
    {
      "label": "Mapping Confidence and No Guessing Rule",
      "file_type": "document",
      "source_file": "plans/IFC_TO_USDC_CONVERSION_API_IMPLEMENTATION_PLAN.md",
      "source_location": "section 11.3",
      "source_url": null,
      "captured_at": null,
      "author": null,
      "contributor": null,
      "id": "rule_mapping_confidence",
      "community": 3,
      "norm_label": "mapping confidence and no guessing rule"
    },
    {
      "label": "Use One Root Repo Instead of Nested Git",
      "file_type": "document",
      "source_file": "git/nested-repo-remotes.md",
      "source_location": "Created while consolidating",
      "source_url": null,
      "captured_at": null,
      "author": null,
      "contributor": null,
      "id": "rule_single_root_repo",
      "community": 2,
      "norm_label": "use one root repo instead of nested git"
    },
    {
      "label": "USDC Mapping Coverage Low",
      "file_type": "document",
      "source_file": "plans/BIM_REVIEW_COORDINATOR_WEB_VIEWER_EXECUTION_PLAN.md",
      "source_location": "section 17.2",
      "source_url": null,
      "captured_at": null,
      "author": null,
      "contributor": null,
      "id": "risk_mapping_low",
      "community": 3,
      "norm_label": "usdc mapping coverage low"
    },
    {
      "label": "WebRTC Server Not Running",
      "file_type": "document",
      "source_file": "plans/BIM_REVIEW_COORDINATOR_WEB_VIEWER_EXECUTION_PLAN.md",
      "source_location": "section 17.4",
      "source_url": null,
      "captured_at": null,
      "author": null,
      "contributor": null,
      "id": "risk_webrtc_down",
      "community": 4,
      "norm_label": "webrtc server not running"
    },
    {
      "label": "Conversion Result Not Ready",
      "file_type": "document",
      "source_file": "plans/BIM_REVIEW_COORDINATOR_WEB_VIEWER_EXECUTION_PLAN.md",
      "source_location": "section 17.1",
      "source_url": null,
      "captured_at": null,
      "author": null,
      "contributor": null,
      "id": "risk_conversion_not_ready",
      "community": 0,
      "norm_label": "conversion result not ready"
    },
    {
      "label": "localhost:8001 Fake BIM Control",
      "file_type": "document",
      "source_file": "contracts/bim-control-fake-api.md",
      "source_location": "Base URL",
      "source_url": null,
      "captured_at": null,
      "author": null,
      "contributor": null,
      "id": "port_8001_bim_control",
      "community": 2,
      "norm_label": "localhost:8001 fake bim control"
    },
    {
      "label": "localhost:8002 Fake Storage",
      "file_type": "document",
      "source_file": "contracts/conversion-api.md",
      "source_location": "Create Conversion",
      "source_url": null,
      "captured_at": null,
      "author": null,
      "contributor": null,
      "id": "port_8002_s3_storage",
      "community": 2,
      "norm_label": "localhost:8002 fake storage"
    },
    {
      "label": "localhost:8003 Conversion Service",
      "file_type": "document",
      "source_file": "contracts/conversion-api.md",
      "source_location": "Base URL",
      "source_url": null,
      "captured_at": null,
      "author": null,
      "contributor": null,
      "id": "port_8003_conversion",
      "community": 2,
      "norm_label": "localhost:8003 conversion service"
    },
    {
      "label": "localhost:8004 Review Coordinator",
      "file_type": "document",
      "source_file": "contracts/review-session-api.md",
      "source_location": "Base URL",
      "source_url": null,
      "captured_at": null,
      "author": null,
      "contributor": null,
      "id": "port_8004_coordinator",
      "community": 4,
      "norm_label": "localhost:8004 review coordinator"
    },
    {
      "label": "127.0.0.1:49100 WebRTC Signaling",
      "file_type": "document",
      "source_file": "contracts/review-session-api.md",
      "source_location": "Create Session",
      "source_url": null,
      "captured_at": null,
      "author": null,
      "contributor": null,
      "id": "port_49100_webrtc",
      "community": 4,
      "norm_label": "127.0.0.1:49100 webrtc signaling"
    },
    {
      "label": "localhost:5173 Web Viewer",
      "file_type": "document",
      "source_file": "contracts/local-dev-runbook.md",
      "source_location": "Web Viewer",
      "source_url": null,
      "captured_at": null,
      "author": null,
      "contributor": null,
      "id": "port_5173_web_viewer",
      "community": 2,
      "norm_label": "localhost:5173 web viewer"
    }
  ],
  "links": [
    {
      "relation": "references",
      "confidence": "EXTRACTED",
      "confidence_score": 1.0,
      "source_file": "plans/BIM_REVIEW_COORDINATOR_WEB_VIEWER_EXECUTION_PLAN.md",
      "source_location": null,
      "weight": 1.0,
      "_src": "doc_review_web_plan",
      "_tgt": "flow_review_session_bootstrap",
      "source": "doc_review_web_plan",
      "target": "flow_review_session_bootstrap"
    },
    {
      "relation": "references",
      "confidence": "EXTRACTED",
      "confidence_score": 1.0,
      "source_file": "plans/BIM_REVIEW_COORDINATOR_WEB_VIEWER_EXECUTION_PLAN.md",
      "source_location": null,
      "weight": 1.0,
      "_src": "doc_review_web_plan",
      "_tgt": "flow_issue_highlight",
      "source": "doc_review_web_plan",
      "target": "flow_issue_highlight"
    },
    {
      "relation": "references",
      "confidence": "INFERRED",
      "confidence_score": 0.88,
      "source_file": "contracts/coordinator-socket-events.md",
      "source_location": "Socket.IO /review",
      "weight": 1.0,
      "_src": "doc_socket_contract",
      "_tgt": "doc_review_web_plan",
      "source": "doc_review_web_plan",
      "target": "doc_socket_contract"
    },
    {
      "relation": "references",
      "confidence": "EXTRACTED",
      "confidence_score": 1.0,
      "source_file": "plans/IFC_TO_USDC_CONVERSION_API_IMPLEMENTATION_PLAN.md",
      "source_location": null,
      "weight": 1.0,
      "_src": "doc_ifc_usdc_plan",
      "_tgt": "flow_conversion_publish",
      "source": "doc_ifc_usdc_plan",
      "target": "flow_conversion_publish"
    },
    {
      "relation": "references",
      "confidence": "EXTRACTED",
      "confidence_score": 1.0,
      "source_file": "plans/IFC_TO_USDC_CONVERSION_API_IMPLEMENTATION_PLAN.md",
      "source_location": null,
      "weight": 1.0,
      "_src": "doc_ifc_usdc_plan",
      "_tgt": "flow_e2e_browser_validation",
      "source": "doc_ifc_usdc_plan",
      "target": "flow_e2e_browser_validation"
    },
    {
      "relation": "references",
      "confidence": "INFERRED",
      "confidence_score": 0.84,
      "source_file": "contracts/streaming-datachannel-events.md",
      "source_location": "openStageRequest validation",
      "weight": 1.0,
      "_src": "doc_datachannel_contract",
      "_tgt": "doc_ifc_usdc_plan",
      "source": "doc_ifc_usdc_plan",
      "target": "doc_datachannel_contract"
    },
    {
      "relation": "references",
      "confidence": "EXTRACTED",
      "confidence_score": 1.0,
      "source_file": "contracts/review-session-api.md",
      "source_location": null,
      "weight": 1.0,
      "_src": "doc_review_session_api",
      "_tgt": "api_post_review_sessions",
      "source": "doc_review_session_api",
      "target": "api_post_review_sessions"
    },
    {
      "relation": "references",
      "confidence": "EXTRACTED",
      "confidence_score": 1.0,
      "source_file": "contracts/review-session-api.md",
      "source_location": null,
      "weight": 1.0,
      "_src": "doc_review_session_api",
      "_tgt": "api_get_stream_config",
      "source": "doc_review_session_api",
      "target": "api_get_stream_config"
    },
    {
      "relation": "semantically_similar_to",
      "confidence": "INFERRED",
      "confidence_score": 0.82,
      "source_file": "contracts/conversion-api.md",
      "source_location": "ready USDC discovery",
      "weight": 1.0,
      "_src": "doc_conversion_api",
      "_tgt": "doc_review_session_api",
      "source": "doc_review_session_api",
      "target": "doc_conversion_api"
    },
    {
      "relation": "references",
      "confidence": "EXTRACTED",
      "confidence_score": 1.0,
      "source_file": "contracts/streaming-datachannel-events.md",
      "source_location": null,
      "weight": 1.0,
      "_src": "doc_datachannel_contract",
      "_tgt": "dc_open_stage_request",
      "source": "doc_datachannel_contract",
      "target": "dc_open_stage_request"
    },
    {
      "relation": "references",
      "confidence": "EXTRACTED",
      "confidence_score": 1.0,
      "source_file": "contracts/streaming-datachannel-events.md",
      "source_location": null,
      "weight": 1.0,
      "_src": "doc_datachannel_contract",
      "_tgt": "dc_highlight_prims_request",
      "source": "doc_datachannel_contract",
      "target": "dc_highlight_prims_request"
    },
    {
      "relation": "references",
      "confidence": "EXTRACTED",
      "confidence_score": 1.0,
      "source_file": "contracts/coordinator-socket-events.md",
      "source_location": null,
      "weight": 1.0,
      "_src": "doc_socket_contract",
      "_tgt": "socket_highlight_request",
      "source": "doc_socket_contract",
      "target": "socket_highlight_request"
    },
    {
      "relation": "references",
      "confidence": "EXTRACTED",
      "confidence_score": 1.0,
      "source_file": "contracts/conversion-api.md",
      "source_location": null,
      "weight": 1.0,
      "_src": "doc_conversion_api",
      "_tgt": "api_post_conversions",
      "source": "doc_conversion_api",
      "target": "api_post_conversions"
    },
    {
      "relation": "references",
      "confidence": "EXTRACTED",
      "confidence_score": 1.0,
      "source_file": "contracts/bim-control-fake-api.md",
      "source_location": null,
      "weight": 1.0,
      "_src": "doc_bim_control_api",
      "_tgt": "api_post_conversion_result",
      "source": "doc_bim_control_api",
      "target": "api_post_conversion_result"
    },
    {
      "relation": "references",
      "confidence": "EXTRACTED",
      "confidence_score": 1.0,
      "source_file": "contracts/local-dev-runbook.md",
      "source_location": null,
      "weight": 1.0,
      "_src": "doc_local_runbook",
      "_tgt": "flow_local_run_sequence",
      "source": "doc_local_runbook",
      "target": "flow_local_run_sequence"
    },
    {
      "relation": "conceptually_related_to",
      "confidence": "INFERRED",
      "confidence_score": 0.76,
      "source_file": "git/nested-repo-remotes.md",
      "source_location": null,
      "weight": 1.0,
      "_src": "rule_single_root_repo",
      "_tgt": "doc_local_runbook",
      "source": "doc_local_runbook",
      "target": "rule_single_root_repo"
    },
    {
      "relation": "references",
      "confidence": "EXTRACTED",
      "confidence_score": 1.0,
      "source_file": "git/nested-repo-remotes.md",
      "source_location": null,
      "weight": 1.0,
      "_src": "doc_nested_repo_remote_record",
      "_tgt": "rule_single_root_repo",
      "source": "doc_nested_repo_remote_record",
      "target": "rule_single_root_repo"
    },
    {
      "relation": "references",
      "confidence": "EXTRACTED",
      "confidence_score": 1.0,
      "source_file": "git/nested-repo-remotes.md",
      "source_location": null,
      "weight": 1.0,
      "_src": "repo_ai_bim_governance",
      "_tgt": "git_root_remote",
      "source": "repo_ai_bim_governance",
      "target": "git_root_remote"
    },
    {
      "relation": "contains",
      "confidence": "EXTRACTED",
      "confidence_score": 1.0,
      "source_file": "git/nested-repo-remotes.md",
      "source_location": null,
      "weight": 1.0,
      "_src": "repo_ai_bim_governance",
      "_tgt": "repo_absorbed_bim_streaming",
      "source": "repo_ai_bim_governance",
      "target": "repo_absorbed_bim_streaming"
    },
    {
      "relation": "contains",
      "confidence": "EXTRACTED",
      "confidence_score": 1.0,
      "source_file": "git/nested-repo-remotes.md",
      "source_location": null,
      "weight": 1.0,
      "_src": "repo_ai_bim_governance",
      "_tgt": "repo_absorbed_web_viewer",
      "source": "repo_ai_bim_governance",
      "target": "repo_absorbed_web_viewer"
    },
    {
      "relation": "rationale_for",
      "confidence": "INFERRED",
      "confidence_score": 0.86,
      "source_file": "git/nested-repo-remotes.md",
      "source_location": null,
      "weight": 1.0,
      "_src": "rule_single_root_repo",
      "_tgt": "repo_ai_bim_governance",
      "source": "repo_ai_bim_governance",
      "target": "rule_single_root_repo"
    },
    {
      "relation": "conceptually_related_to",
      "confidence": "INFERRED",
      "confidence_score": 0.72,
      "source_file": "contracts/local-dev-runbook.md",
      "source_location": null,
      "weight": 1.0,
      "_src": "repo_ai_bim_governance",
      "_tgt": "flow_local_run_sequence",
      "source": "repo_ai_bim_governance",
      "target": "flow_local_run_sequence"
    },
    {
      "relation": "implements",
      "confidence": "EXTRACTED",
      "confidence_score": 1.0,
      "source_file": "contracts/conversion-api.md",
      "source_location": null,
      "weight": 1.0,
      "_src": "service_conversion_service",
      "_tgt": "api_post_conversions",
      "source": "service_conversion_service",
      "target": "api_post_conversions"
    },
    {
      "relation": "implements",
      "confidence": "EXTRACTED",
      "confidence_score": 1.0,
      "source_file": "contracts/conversion-api.md",
      "source_location": null,
      "weight": 1.0,
      "_src": "service_conversion_service",
      "_tgt": "api_get_conversion_result",
      "source": "service_conversion_service",
      "target": "api_get_conversion_result"
    },
    {
      "relation": "owns",
      "confidence": "EXTRACTED",
      "confidence_score": 1.0,
      "source_file": "plans/IFC_TO_USDC_CONVERSION_API_IMPLEMENTATION_PLAN.md",
      "source_location": null,
      "weight": 1.0,
      "_src": "service_conversion_service",
      "_tgt": "data_conversion_job",
      "source": "service_conversion_service",
      "target": "data_conversion_job"
    },
    {
      "relation": "calls",
      "confidence": "EXTRACTED",
      "confidence_score": 1.0,
      "source_file": "plans/IFC_TO_USDC_CONVERSION_API_IMPLEMENTATION_PLAN.md",
      "source_location": "section 1.1",
      "weight": 1.0,
      "_src": "service_conversion_service",
      "_tgt": "service_bim_streaming_server",
      "source": "service_conversion_service",
      "target": "service_bim_streaming_server"
    },
    {
      "relation": "implements",
      "confidence": "EXTRACTED",
      "confidence_score": 1.0,
      "source_file": "plans/IFC_TO_USDC_CONVERSION_API_IMPLEMENTATION_PLAN.md",
      "source_location": null,
      "weight": 1.0,
      "_src": "service_conversion_service",
      "_tgt": "flow_conversion_publish",
      "source": "service_conversion_service",
      "target": "flow_conversion_publish"
    },
    {
      "relation": "rationale_for",
      "confidence": "EXTRACTED",
      "confidence_score": 1.0,
      "source_file": "plans/BIM_REVIEW_COORDINATOR_WEB_VIEWER_EXECUTION_PLAN.md",
      "source_location": "section 18",
      "weight": 1.0,
      "_src": "rule_conversion_service_pluggable",
      "_tgt": "service_conversion_service",
      "source": "service_conversion_service",
      "target": "rule_conversion_service_pluggable"
    },
    {
      "relation": "serves",
      "confidence": "EXTRACTED",
      "confidence_score": 1.0,
      "source_file": "contracts/conversion-api.md",
      "source_location": null,
      "weight": 1.0,
      "_src": "port_8003_conversion",
      "_tgt": "service_conversion_service",
      "source": "service_conversion_service",
      "target": "port_8003_conversion"
    },
    {
      "relation": "conceptually_related_to",
      "confidence": "INFERRED",
      "confidence_score": 0.78,
      "source_file": "git/nested-repo-remotes.md",
      "source_location": null,
      "weight": 1.0,
      "_src": "rule_single_root_repo",
      "_tgt": "service_bim_streaming_server",
      "source": "service_bim_streaming_server",
      "target": "rule_single_root_repo"
    },
    {
      "relation": "loads",
      "confidence": "EXTRACTED",
      "confidence_score": 1.0,
      "source_file": "contracts/streaming-datachannel-events.md",
      "source_location": null,
      "weight": 1.0,
      "_src": "service_bim_streaming_server",
      "_tgt": "data_usdc_model",
      "source": "service_bim_streaming_server",
      "target": "data_usdc_model"
    },
    {
      "relation": "implements",
      "confidence": "EXTRACTED",
      "confidence_score": 1.0,
      "source_file": "contracts/streaming-datachannel-events.md",
      "source_location": null,
      "weight": 1.0,
      "_src": "service_bim_streaming_server",
      "_tgt": "dc_open_stage_request",
      "source": "service_bim_streaming_server",
      "target": "dc_open_stage_request"
    },
    {
      "relation": "implements",
      "confidence": "EXTRACTED",
      "confidence_score": 1.0,
      "source_file": "contracts/streaming-datachannel-events.md",
      "source_location": null,
      "weight": 1.0,
      "_src": "service_bim_streaming_server",
      "_tgt": "dc_highlight_prims_request",
      "source": "service_bim_streaming_server",
      "target": "dc_highlight_prims_request"
    },
    {
      "relation": "uses",
      "confidence": "EXTRACTED",
      "confidence_score": 1.0,
      "source_file": "contracts/review-session-api.md",
      "source_location": null,
      "weight": 1.0,
      "_src": "service_bim_streaming_server",
      "_tgt": "port_49100_webrtc",
      "source": "service_bim_streaming_server",
      "target": "port_49100_webrtc"
    },
    {
      "relation": "targets",
      "confidence": "EXTRACTED",
      "confidence_score": 1.0,
      "source_file": "contracts/streaming-datachannel-events.md",
      "source_location": null,
      "weight": 1.0,
      "_src": "flow_streaming_open_stage",
      "_tgt": "service_bim_streaming_server",
      "source": "service_bim_streaming_server",
      "target": "flow_streaming_open_stage"
    },
    {
      "relation": "uses",
      "confidence": "EXTRACTED",
      "confidence_score": 1.0,
      "source_file": "plans/IFC_TO_USDC_CONVERSION_API_IMPLEMENTATION_PLAN.md",
      "source_location": "Final Acceptance",
      "weight": 1.0,
      "_src": "flow_e2e_browser_validation",
      "_tgt": "service_bim_streaming_server",
      "source": "service_bim_streaming_server",
      "target": "flow_e2e_browser_validation"
    },
    {
      "relation": "owns",
      "confidence": "EXTRACTED",
      "confidence_score": 1.0,
      "source_file": "plans/IFC_TO_USDC_CONVERSION_API_IMPLEMENTATION_PLAN.md",
      "source_location": null,
      "weight": 1.0,
      "_src": "service_s3_storage",
      "_tgt": "data_ifc_file",
      "source": "service_s3_storage",
      "target": "data_ifc_file"
    },
    {
      "relation": "owns",
      "confidence": "EXTRACTED",
      "confidence_score": 1.0,
      "source_file": "plans/IFC_TO_USDC_CONVERSION_API_IMPLEMENTATION_PLAN.md",
      "source_location": null,
      "weight": 1.0,
      "_src": "service_s3_storage",
      "_tgt": "data_usdc_model",
      "source": "service_s3_storage",
      "target": "data_usdc_model"
    },
    {
      "relation": "owns",
      "confidence": "EXTRACTED",
      "confidence_score": 1.0,
      "source_file": "contracts/conversion-api.md",
      "source_location": null,
      "weight": 1.0,
      "_src": "service_s3_storage",
      "_tgt": "data_ifc_index",
      "source": "service_s3_storage",
      "target": "data_ifc_index"
    },
    {
      "relation": "owns",
      "confidence": "EXTRACTED",
      "confidence_score": 1.0,
      "source_file": "contracts/conversion-api.md",
      "source_location": null,
      "weight": 1.0,
      "_src": "service_s3_storage",
      "_tgt": "data_usd_index",
      "source": "service_s3_storage",
      "target": "data_usd_index"
    },
    {
      "relation": "owns",
      "confidence": "EXTRACTED",
      "confidence_score": 1.0,
      "source_file": "contracts/conversion-api.md",
      "source_location": null,
      "weight": 1.0,
      "_src": "service_s3_storage",
      "_tgt": "data_element_mapping",
      "source": "service_s3_storage",
      "target": "data_element_mapping"
    },
    {
      "relation": "rationale_for",
      "confidence": "EXTRACTED",
      "confidence_score": 1.0,
      "source_file": "contracts/bim-control-fake-api.md",
      "source_location": null,
      "weight": 1.0,
      "_src": "rule_metadata_vs_bytes",
      "_tgt": "service_s3_storage",
      "source": "service_s3_storage",
      "target": "rule_metadata_vs_bytes"
    },
    {
      "relation": "writes_to",
      "confidence": "EXTRACTED",
      "confidence_score": 1.0,
      "source_file": "plans/IFC_TO_USDC_CONVERSION_API_IMPLEMENTATION_PLAN.md",
      "source_location": "section 12",
      "weight": 1.0,
      "_src": "flow_conversion_publish",
      "_tgt": "service_s3_storage",
      "source": "service_s3_storage",
      "target": "flow_conversion_publish"
    },
    {
      "relation": "resolves",
      "confidence": "EXTRACTED",
      "confidence_score": 1.0,
      "source_file": "plans/BIM_REVIEW_COORDINATOR_WEB_VIEWER_EXECUTION_PLAN.md",
      "source_location": null,
      "weight": 1.0,
      "_src": "flow_artifact_discovery",
      "_tgt": "service_s3_storage",
      "source": "service_s3_storage",
      "target": "flow_artifact_discovery"
    },
    {
      "relation": "serves",
      "confidence": "EXTRACTED",
      "confidence_score": 1.0,
      "source_file": "contracts/conversion-api.md",
      "source_location": null,
      "weight": 1.0,
      "_src": "port_8002_s3_storage",
      "_tgt": "service_s3_storage",
      "source": "service_s3_storage",
      "target": "port_8002_s3_storage"
    },
    {
      "relation": "owns",
      "confidence": "EXTRACTED",
      "confidence_score": 1.0,
      "source_file": "contracts/bim-control-fake-api.md",
      "source_location": null,
      "weight": 1.0,
      "_src": "service_bim_control",
      "_tgt": "data_artifact_metadata",
      "source": "service_bim_control",
      "target": "data_artifact_metadata"
    },
    {
      "relation": "owns",
      "confidence": "EXTRACTED",
      "confidence_score": 1.0,
      "source_file": "contracts/bim-control-fake-api.md",
      "source_location": null,
      "weight": 1.0,
      "_src": "service_bim_control",
      "_tgt": "data_review_issue",
      "source": "service_bim_control",
      "target": "data_review_issue"
    },
    {
      "relation": "owns",
      "confidence": "EXTRACTED",
      "confidence_score": 1.0,
      "source_file": "contracts/bim-control-fake-api.md",
      "source_location": null,
      "weight": 1.0,
      "_src": "service_bim_control",
      "_tgt": "data_annotation",
      "source": "service_bim_control",
      "target": "data_annotation"
    },
    {
      "relation": "rationale_for",
      "confidence": "EXTRACTED",
      "confidence_score": 1.0,
      "source_file": "contracts/bim-control-fake-api.md",
      "source_location": null,
      "weight": 1.0,
      "_src": "rule_metadata_vs_bytes",
      "_tgt": "service_bim_control",
      "source": "service_bim_control",
      "target": "rule_metadata_vs_bytes"
    },
    {
      "relation": "writes_to",
      "confidence": "EXTRACTED",
      "confidence_score": 1.0,
      "source_file": "plans/IFC_TO_USDC_CONVERSION_API_IMPLEMENTATION_PLAN.md",
      "source_location": "section 12",
      "weight": 1.0,
      "_src": "flow_conversion_publish",
      "_tgt": "service_bim_control",
      "source": "service_bim_control",
      "target": "flow_conversion_publish"
    },
    {
      "relation": "queries",
      "confidence": "EXTRACTED",
      "confidence_score": 1.0,
      "source_file": "plans/BIM_REVIEW_COORDINATOR_WEB_VIEWER_EXECUTION_PLAN.md",
      "source_location": null,
      "weight": 1.0,
      "_src": "flow_artifact_discovery",
      "_tgt": "service_bim_control",
      "source": "service_bim_control",
      "target": "flow_artifact_discovery"
    },
    {
      "relation": "writes_to",
      "confidence": "EXTRACTED",
      "confidence_score": 1.0,
      "source_file": "contracts/coordinator-socket-events.md",
      "source_location": null,
      "weight": 1.0,
      "_src": "flow_annotation_persist",
      "_tgt": "service_bim_control",
      "source": "service_bim_control",
      "target": "flow_annotation_persist"
    },
    {
      "relation": "serves",
      "confidence": "EXTRACTED",
      "confidence_score": 1.0,
      "source_file": "contracts/bim-control-fake-api.md",
      "source_location": null,
      "weight": 1.0,
      "_src": "port_8001_bim_control",
      "_tgt": "service_bim_control",
      "source": "service_bim_control",
      "target": "port_8001_bim_control"
    },
    {
      "relation": "conceptually_related_to",
      "confidence": "INFERRED",
      "confidence_score": 0.78,
      "source_file": "git/nested-repo-remotes.md",
      "source_location": null,
      "weight": 1.0,
      "_src": "rule_single_root_repo",
      "_tgt": "service_web_viewer",
      "source": "service_web_viewer",
      "target": "rule_single_root_repo"
    },
    {
      "relation": "sends",
      "confidence": "EXTRACTED",
      "confidence_score": 1.0,
      "source_file": "contracts/streaming-datachannel-events.md",
      "source_location": null,
      "weight": 1.0,
      "_src": "service_web_viewer",
      "_tgt": "dc_open_stage_request",
      "source": "service_web_viewer",
      "target": "dc_open_stage_request"
    },
    {
      "relation": "sends",
      "confidence": "EXTRACTED",
      "confidence_score": 1.0,
      "source_file": "contracts/streaming-datachannel-events.md",
      "source_location": null,
      "weight": 1.0,
      "_src": "service_web_viewer",
      "_tgt": "dc_highlight_prims_request",
      "source": "service_web_viewer",
      "target": "dc_highlight_prims_request"
    },
    {
      "relation": "serves",
      "confidence": "EXTRACTED",
      "confidence_score": 1.0,
      "source_file": "contracts/local-dev-runbook.md",
      "source_location": null,
      "weight": 1.0,
      "_src": "port_5173_web_viewer",
      "_tgt": "service_web_viewer",
      "source": "service_web_viewer",
      "target": "port_5173_web_viewer"
    },
    {
      "relation": "uses",
      "confidence": "EXTRACTED",
      "confidence_score": 1.0,
      "source_file": "plans/IFC_TO_USDC_CONVERSION_API_IMPLEMENTATION_PLAN.md",
      "source_location": "Final Acceptance",
      "weight": 1.0,
      "_src": "flow_e2e_browser_validation",
      "_tgt": "service_web_viewer",
      "source": "service_web_viewer",
      "target": "flow_e2e_browser_validation"
    },
    {
      "relation": "owns",
      "confidence": "EXTRACTED",
      "confidence_score": 1.0,
      "source_file": "contracts/review-session-api.md",
      "source_location": null,
      "weight": 1.0,
      "_src": "service_review_coordinator",
      "_tgt": "data_review_session",
      "source": "service_review_coordinator",
      "target": "data_review_session"
    },
    {
      "relation": "owns",
      "confidence": "EXTRACTED",
      "confidence_score": 1.0,
      "source_file": "contracts/review-session-api.md",
      "source_location": null,
      "weight": 1.0,
      "_src": "service_review_coordinator",
      "_tgt": "data_stream_config",
      "source": "service_review_coordinator",
      "target": "data_stream_config"
    },
    {
      "relation": "uses",
      "confidence": "EXTRACTED",
      "confidence_score": 1.0,
      "source_file": "plans/BIM_REVIEW_COORDINATOR_WEB_VIEWER_EXECUTION_PLAN.md",
      "source_location": null,
      "weight": 1.0,
      "_src": "flow_artifact_discovery",
      "_tgt": "service_review_coordinator",
      "source": "service_review_coordinator",
      "target": "flow_artifact_discovery"
    },
    {
      "relation": "serves",
      "confidence": "EXTRACTED",
      "confidence_score": 1.0,
      "source_file": "contracts/review-session-api.md",
      "source_location": null,
      "weight": 1.0,
      "_src": "port_8004_coordinator",
      "_tgt": "service_review_coordinator",
      "source": "service_review_coordinator",
      "target": "port_8004_coordinator"
    },
    {
      "relation": "references",
      "confidence": "EXTRACTED",
      "confidence_score": 1.0,
      "source_file": "git/nested-repo-remotes.md",
      "source_location": null,
      "weight": 1.0,
      "_src": "repo_absorbed_bim_streaming",
      "_tgt": "git_nested_backup",
      "source": "repo_absorbed_bim_streaming",
      "target": "git_nested_backup"
    },
    {
      "relation": "references",
      "confidence": "EXTRACTED",
      "confidence_score": 1.0,
      "source_file": "git/nested-repo-remotes.md",
      "source_location": null,
      "weight": 1.0,
      "_src": "repo_absorbed_web_viewer",
      "_tgt": "git_nested_backup",
      "source": "repo_absorbed_web_viewer",
      "target": "git_nested_backup"
    },
    {
      "relation": "references",
      "confidence": "EXTRACTED",
      "confidence_score": 1.0,
      "source_file": "contracts/conversion-api.md",
      "source_location": null,
      "weight": 1.0,
      "_src": "data_conversion_job",
      "_tgt": "data_ifc_file",
      "source": "data_ifc_file",
      "target": "data_conversion_job"
    },
    {
      "relation": "produces",
      "confidence": "EXTRACTED",
      "confidence_score": 1.0,
      "source_file": "contracts/conversion-api.md",
      "source_location": null,
      "weight": 1.0,
      "_src": "data_conversion_job",
      "_tgt": "data_usdc_model",
      "source": "data_usdc_model",
      "target": "data_conversion_job"
    },
    {
      "relation": "references",
      "confidence": "EXTRACTED",
      "confidence_score": 1.0,
      "source_file": "contracts/review-session-api.md",
      "source_location": null,
      "weight": 1.0,
      "_src": "data_stream_config",
      "_tgt": "data_usdc_model",
      "source": "data_usdc_model",
      "target": "data_stream_config"
    },
    {
      "relation": "references",
      "confidence": "EXTRACTED",
      "confidence_score": 1.0,
      "source_file": "contracts/streaming-datachannel-events.md",
      "source_location": null,
      "weight": 1.0,
      "_src": "dc_open_stage_request",
      "_tgt": "data_usdc_model",
      "source": "data_usdc_model",
      "target": "dc_open_stage_request"
    },
    {
      "relation": "produces",
      "confidence": "EXTRACTED",
      "confidence_score": 1.0,
      "source_file": "contracts/conversion-api.md",
      "source_location": null,
      "weight": 1.0,
      "_src": "data_conversion_job",
      "_tgt": "data_ifc_index",
      "source": "data_ifc_index",
      "target": "data_conversion_job"
    },
    {
      "relation": "references",
      "confidence": "EXTRACTED",
      "confidence_score": 1.0,
      "source_file": "plans/IFC_TO_USDC_CONVERSION_API_IMPLEMENTATION_PLAN.md",
      "source_location": "section 9",
      "weight": 1.0,
      "_src": "data_ifc_index",
      "_tgt": "data_ifc_guid",
      "source": "data_ifc_index",
      "target": "data_ifc_guid"
    },
    {
      "relation": "produces",
      "confidence": "EXTRACTED",
      "confidence_score": 1.0,
      "source_file": "contracts/conversion-api.md",
      "source_location": null,
      "weight": 1.0,
      "_src": "data_conversion_job",
      "_tgt": "data_usd_index",
      "source": "data_usd_index",
      "target": "data_conversion_job"
    },
    {
      "relation": "references",
      "confidence": "EXTRACTED",
      "confidence_score": 1.0,
      "source_file": "plans/IFC_TO_USDC_CONVERSION_API_IMPLEMENTATION_PLAN.md",
      "source_location": "section 10",
      "weight": 1.0,
      "_src": "data_usd_index",
      "_tgt": "data_usd_prim_path",
      "source": "data_usd_index",
      "target": "data_usd_prim_path"
    },
    {
      "relation": "produces",
      "confidence": "EXTRACTED",
      "confidence_score": 1.0,
      "source_file": "contracts/conversion-api.md",
      "source_location": null,
      "weight": 1.0,
      "_src": "data_conversion_job",
      "_tgt": "data_element_mapping",
      "source": "data_element_mapping",
      "target": "data_conversion_job"
    },
    {
      "relation": "maps",
      "confidence": "EXTRACTED",
      "confidence_score": 1.0,
      "source_file": "plans/IFC_TO_USDC_CONVERSION_API_IMPLEMENTATION_PLAN.md",
      "source_location": "section 11",
      "weight": 1.0,
      "_src": "data_element_mapping",
      "_tgt": "data_ifc_guid",
      "source": "data_element_mapping",
      "target": "data_ifc_guid"
    },
    {
      "relation": "maps",
      "confidence": "EXTRACTED",
      "confidence_score": 1.0,
      "source_file": "plans/IFC_TO_USDC_CONVERSION_API_IMPLEMENTATION_PLAN.md",
      "source_location": "section 11",
      "weight": 1.0,
      "_src": "data_element_mapping",
      "_tgt": "data_usd_prim_path",
      "source": "data_element_mapping",
      "target": "data_usd_prim_path"
    },
    {
      "relation": "summarizes",
      "confidence": "EXTRACTED",
      "confidence_score": 1.0,
      "source_file": "plans/IFC_TO_USDC_CONVERSION_API_IMPLEMENTATION_PLAN.md",
      "source_location": "section 11.4",
      "weight": 1.0,
      "_src": "data_element_mapping",
      "_tgt": "data_mapping_summary",
      "source": "data_element_mapping",
      "target": "data_mapping_summary"
    },
    {
      "relation": "rationale_for",
      "confidence": "EXTRACTED",
      "confidence_score": 1.0,
      "source_file": "plans/IFC_TO_USDC_CONVERSION_API_IMPLEMENTATION_PLAN.md",
      "source_location": "section 11.3",
      "weight": 1.0,
      "_src": "rule_mapping_confidence",
      "_tgt": "data_element_mapping",
      "source": "data_element_mapping",
      "target": "rule_mapping_confidence"
    },
    {
      "relation": "references",
      "confidence": "EXTRACTED",
      "confidence_score": 1.0,
      "source_file": "contracts/review-session-api.md",
      "source_location": null,
      "weight": 1.0,
      "_src": "data_stream_config",
      "_tgt": "data_element_mapping",
      "source": "data_element_mapping",
      "target": "data_stream_config"
    },
    {
      "relation": "conceptually_related_to",
      "confidence": "EXTRACTED",
      "confidence_score": 1.0,
      "source_file": "plans/BIM_REVIEW_COORDINATOR_WEB_VIEWER_EXECUTION_PLAN.md",
      "source_location": "section 17.2",
      "weight": 1.0,
      "_src": "risk_mapping_low",
      "_tgt": "data_element_mapping",
      "source": "data_element_mapping",
      "target": "risk_mapping_low"
    },
    {
      "relation": "conceptually_related_to",
      "confidence": "INFERRED",
      "confidence_score": 0.86,
      "source_file": "plans/IFC_TO_USDC_CONVERSION_API_IMPLEMENTATION_PLAN.md",
      "source_location": "mapping enables prim highlight",
      "weight": 1.0,
      "_src": "data_element_mapping",
      "_tgt": "flow_issue_highlight",
      "source": "data_element_mapping",
      "target": "flow_issue_highlight"
    },
    {
      "relation": "references",
      "confidence": "EXTRACTED",
      "confidence_score": 1.0,
      "source_file": "contracts/streaming-datachannel-events.md",
      "source_location": null,
      "weight": 1.0,
      "_src": "dc_highlight_prims_request",
      "_tgt": "data_ifc_guid",
      "source": "data_ifc_guid",
      "target": "dc_highlight_prims_request"
    },
    {
      "relation": "references",
      "confidence": "EXTRACTED",
      "confidence_score": 1.0,
      "source_file": "contracts/streaming-datachannel-events.md",
      "source_location": null,
      "weight": 1.0,
      "_src": "dc_highlight_prims_request",
      "_tgt": "data_usd_prim_path",
      "source": "data_usd_prim_path",
      "target": "dc_highlight_prims_request"
    },
    {
      "relation": "references",
      "confidence": "EXTRACTED",
      "confidence_score": 1.0,
      "source_file": "plans/BIM_REVIEW_COORDINATOR_WEB_VIEWER_EXECUTION_PLAN.md",
      "source_location": null,
      "weight": 1.0,
      "_src": "dc_focus_prim_request",
      "_tgt": "data_usd_prim_path",
      "source": "data_usd_prim_path",
      "target": "dc_focus_prim_request"
    },
    {
      "relation": "references",
      "confidence": "EXTRACTED",
      "confidence_score": 1.0,
      "source_file": "contracts/coordinator-socket-events.md",
      "source_location": null,
      "weight": 1.0,
      "_src": "socket_selection_update",
      "_tgt": "data_usd_prim_path",
      "source": "data_usd_prim_path",
      "target": "socket_selection_update"
    },
    {
      "relation": "updates",
      "confidence": "EXTRACTED",
      "confidence_score": 1.0,
      "source_file": "contracts/bim-control-fake-api.md",
      "source_location": null,
      "weight": 1.0,
      "_src": "api_post_conversion_result",
      "_tgt": "data_artifact_metadata",
      "source": "data_artifact_metadata",
      "target": "api_post_conversion_result"
    },
    {
      "relation": "returns",
      "confidence": "EXTRACTED",
      "confidence_score": 1.0,
      "source_file": "contracts/bim-control-fake-api.md",
      "source_location": null,
      "weight": 1.0,
      "_src": "api_get_artifacts",
      "_tgt": "data_artifact_metadata",
      "source": "data_artifact_metadata",
      "target": "api_get_artifacts"
    },
    {
      "relation": "returns",
      "confidence": "EXTRACTED",
      "confidence_score": 1.0,
      "source_file": "contracts/bim-control-fake-api.md",
      "source_location": null,
      "weight": 1.0,
      "_src": "api_get_review_issues",
      "_tgt": "data_review_issue",
      "source": "data_review_issue",
      "target": "api_get_review_issues"
    },
    {
      "relation": "starts_from",
      "confidence": "EXTRACTED",
      "confidence_score": 1.0,
      "source_file": "plans/BIM_REVIEW_COORDINATOR_WEB_VIEWER_EXECUTION_PLAN.md",
      "source_location": null,
      "weight": 1.0,
      "_src": "flow_issue_highlight",
      "_tgt": "data_review_issue",
      "source": "data_review_issue",
      "target": "flow_issue_highlight"
    },
    {
      "relation": "references",
      "confidence": "EXTRACTED",
      "confidence_score": 1.0,
      "source_file": "contracts/coordinator-socket-events.md",
      "source_location": null,
      "weight": 1.0,
      "_src": "socket_highlight_request",
      "_tgt": "data_review_issue",
      "source": "data_review_issue",
      "target": "socket_highlight_request"
    },
    {
      "relation": "creates",
      "confidence": "EXTRACTED",
      "confidence_score": 1.0,
      "source_file": "contracts/bim-control-fake-api.md",
      "source_location": null,
      "weight": 1.0,
      "_src": "api_post_annotations",
      "_tgt": "data_annotation",
      "source": "data_annotation",
      "target": "api_post_annotations"
    },
    {
      "relation": "creates",
      "confidence": "EXTRACTED",
      "confidence_score": 1.0,
      "source_file": "contracts/review-session-api.md",
      "source_location": null,
      "weight": 1.0,
      "_src": "api_post_review_sessions",
      "_tgt": "data_review_session",
      "source": "data_review_session",
      "target": "api_post_review_sessions"
    },
    {
      "relation": "references",
      "confidence": "EXTRACTED",
      "confidence_score": 1.0,
      "source_file": "contracts/coordinator-socket-events.md",
      "source_location": null,
      "weight": 1.0,
      "_src": "socket_join_session",
      "_tgt": "data_review_session",
      "source": "data_review_session",
      "target": "socket_join_session"
    },
    {
      "relation": "returns",
      "confidence": "EXTRACTED",
      "confidence_score": 1.0,
      "source_file": "contracts/review-session-api.md",
      "source_location": null,
      "weight": 1.0,
      "_src": "api_get_stream_config",
      "_tgt": "data_stream_config",
      "source": "data_stream_config",
      "target": "api_get_stream_config"
    },
    {
      "relation": "references",
      "confidence": "EXTRACTED",
      "confidence_score": 1.0,
      "source_file": "contracts/review-session-api.md",
      "source_location": null,
      "weight": 1.0,
      "_src": "data_stream_config",
      "_tgt": "port_49100_webrtc",
      "source": "data_stream_config",
      "target": "port_49100_webrtc"
    },
    {
      "relation": "creates",
      "confidence": "EXTRACTED",
      "confidence_score": 1.0,
      "source_file": "contracts/conversion-api.md",
      "source_location": null,
      "weight": 1.0,
      "_src": "api_post_conversions",
      "_tgt": "data_conversion_job",
      "source": "data_conversion_job",
      "target": "api_post_conversions"
    },
    {
      "relation": "updates",
      "confidence": "EXTRACTED",
      "confidence_score": 1.0,
      "source_file": "contracts/conversion-api.md",
      "source_location": null,
      "weight": 1.0,
      "_src": "data_conversion_result",
      "_tgt": "api_post_conversion_result",
      "source": "data_conversion_result",
      "target": "api_post_conversion_result"
    },
    {
      "relation": "conceptually_related_to",
      "confidence": "INFERRED",
      "confidence_score": 0.88,
      "source_file": "contracts/conversion-api.md",
      "source_location": "coordinator discovers ready artifact",
      "weight": 1.0,
      "_src": "data_conversion_result",
      "_tgt": "flow_artifact_discovery",
      "source": "data_conversion_result",
      "target": "flow_artifact_discovery"
    },
    {
      "relation": "calls",
      "confidence": "EXTRACTED",
      "confidence_score": 1.0,
      "source_file": "contracts/coordinator-socket-events.md",
      "source_location": null,
      "weight": 1.0,
      "_src": "socket_annotation_create",
      "_tgt": "api_post_annotations",
      "source": "api_post_annotations",
      "target": "socket_annotation_create"
    },
    {
      "relation": "calls",
      "confidence": "EXTRACTED",
      "confidence_score": 1.0,
      "source_file": "plans/BIM_REVIEW_COORDINATOR_WEB_VIEWER_EXECUTION_PLAN.md",
      "source_location": null,
      "weight": 1.0,
      "_src": "flow_review_session_bootstrap",
      "_tgt": "api_post_review_sessions",
      "source": "api_post_review_sessions",
      "target": "flow_review_session_bootstrap"
    },
    {
      "relation": "calls",
      "confidence": "EXTRACTED",
      "confidence_score": 1.0,
      "source_file": "plans/BIM_REVIEW_COORDINATOR_WEB_VIEWER_EXECUTION_PLAN.md",
      "source_location": null,
      "weight": 1.0,
      "_src": "flow_review_session_bootstrap",
      "_tgt": "api_get_stream_config",
      "source": "api_get_stream_config",
      "target": "flow_review_session_bootstrap"
    },
    {
      "relation": "supports",
      "confidence": "EXTRACTED",
      "confidence_score": 1.0,
      "source_file": "contracts/review-session-api.md",
      "source_location": null,
      "weight": 1.0,
      "_src": "api_get_review_bootstrap",
      "_tgt": "flow_review_session_bootstrap",
      "source": "api_get_review_bootstrap",
      "target": "flow_review_session_bootstrap"
    },
    {
      "relation": "returns",
      "confidence": "EXTRACTED",
      "confidence_score": 1.0,
      "source_file": "contracts/coordinator-socket-events.md",
      "source_location": null,
      "weight": 1.0,
      "_src": "socket_presence_updated",
      "_tgt": "socket_join_session",
      "source": "socket_join_session",
      "target": "socket_presence_updated"
    },
    {
      "relation": "broadcasts",
      "confidence": "EXTRACTED",
      "confidence_score": 1.0,
      "source_file": "contracts/coordinator-socket-events.md",
      "source_location": null,
      "weight": 1.0,
      "_src": "flow_issue_highlight",
      "_tgt": "socket_highlight_request",
      "source": "socket_highlight_request",
      "target": "flow_issue_highlight"
    },
    {
      "relation": "uses",
      "confidence": "EXTRACTED",
      "confidence_score": 1.0,
      "source_file": "contracts/coordinator-socket-events.md",
      "source_location": null,
      "weight": 1.0,
      "_src": "flow_annotation_persist",
      "_tgt": "socket_annotation_create",
      "source": "socket_annotation_create",
      "target": "flow_annotation_persist"
    },
    {
      "relation": "rationale_for",
      "confidence": "EXTRACTED",
      "confidence_score": 1.0,
      "source_file": "plans/BIM_REVIEW_COORDINATOR_WEB_VIEWER_EXECUTION_PLAN.md",
      "source_location": "section 17.1",
      "weight": 1.0,
      "_src": "rule_missing_usdc_gate",
      "_tgt": "dc_open_stage_request",
      "source": "dc_open_stage_request",
      "target": "rule_missing_usdc_gate"
    },
    {
      "relation": "uses",
      "confidence": "EXTRACTED",
      "confidence_score": 1.0,
      "source_file": "contracts/streaming-datachannel-events.md",
      "source_location": null,
      "weight": 1.0,
      "_src": "flow_streaming_open_stage",
      "_tgt": "dc_open_stage_request",
      "source": "dc_open_stage_request",
      "target": "flow_streaming_open_stage"
    },
    {
      "relation": "returns",
      "confidence": "EXTRACTED",
      "confidence_score": 1.0,
      "source_file": "contracts/streaming-datachannel-events.md",
      "source_location": null,
      "weight": 1.0,
      "_src": "dc_open_stage_request",
      "_tgt": "dc_opened_stage_result",
      "source": "dc_open_stage_request",
      "target": "dc_opened_stage_result"
    },
    {
      "relation": "verifies",
      "confidence": "EXTRACTED",
      "confidence_score": 1.0,
      "source_file": "plans/IFC_TO_USDC_CONVERSION_API_IMPLEMENTATION_PLAN.md",
      "source_location": "Final Acceptance",
      "weight": 1.0,
      "_src": "flow_e2e_browser_validation",
      "_tgt": "dc_open_stage_request",
      "source": "dc_open_stage_request",
      "target": "flow_e2e_browser_validation"
    },
    {
      "relation": "uses",
      "confidence": "EXTRACTED",
      "confidence_score": 1.0,
      "source_file": "contracts/streaming-datachannel-events.md",
      "source_location": null,
      "weight": 1.0,
      "_src": "flow_issue_highlight",
      "_tgt": "dc_highlight_prims_request",
      "source": "dc_highlight_prims_request",
      "target": "flow_issue_highlight"
    },
    {
      "relation": "returns",
      "confidence": "EXTRACTED",
      "confidence_score": 1.0,
      "source_file": "contracts/streaming-datachannel-events.md",
      "source_location": null,
      "weight": 1.0,
      "_src": "dc_highlight_prims_request",
      "_tgt": "dc_highlight_prims_result",
      "source": "dc_highlight_prims_request",
      "target": "dc_highlight_prims_result"
    },
    {
      "relation": "conceptually_related_to",
      "confidence": "EXTRACTED",
      "confidence_score": 1.0,
      "source_file": "plans/BIM_REVIEW_COORDINATOR_WEB_VIEWER_EXECUTION_PLAN.md",
      "source_location": null,
      "weight": 1.0,
      "_src": "dc_clear_highlight_request",
      "_tgt": "dc_highlight_prims_request",
      "source": "dc_highlight_prims_request",
      "target": "dc_clear_highlight_request"
    },
    {
      "relation": "verifies",
      "confidence": "EXTRACTED",
      "confidence_score": 1.0,
      "source_file": "plans/IFC_TO_USDC_CONVERSION_API_IMPLEMENTATION_PLAN.md",
      "source_location": "Final Acceptance",
      "weight": 1.0,
      "_src": "flow_e2e_browser_validation",
      "_tgt": "dc_highlight_prims_request",
      "source": "dc_highlight_prims_request",
      "target": "flow_e2e_browser_validation"
    },
    {
      "relation": "rationale_for",
      "confidence": "EXTRACTED",
      "confidence_score": 1.0,
      "source_file": "contracts/streaming-datachannel-events.md",
      "source_location": null,
      "weight": 1.0,
      "_src": "rule_highlight_fallback",
      "_tgt": "dc_highlight_prims_result",
      "source": "dc_highlight_prims_result",
      "target": "rule_highlight_fallback"
    },
    {
      "relation": "rationale_for",
      "confidence": "INFERRED",
      "confidence_score": 0.8,
      "source_file": "plans/BIM_REVIEW_COORDINATOR_WEB_VIEWER_EXECUTION_PLAN.md",
      "source_location": null,
      "weight": 1.0,
      "_src": "rule_conversion_service_pluggable",
      "_tgt": "flow_conversion_publish",
      "source": "flow_conversion_publish",
      "target": "rule_conversion_service_pluggable"
    },
    {
      "relation": "rationale_for",
      "confidence": "INFERRED",
      "confidence_score": 0.82,
      "source_file": "contracts/bim-control-fake-api.md",
      "source_location": null,
      "weight": 1.0,
      "_src": "rule_metadata_vs_bytes",
      "_tgt": "flow_artifact_discovery",
      "source": "flow_artifact_discovery",
      "target": "rule_metadata_vs_bytes"
    },
    {
      "relation": "starts",
      "confidence": "EXTRACTED",
      "confidence_score": 1.0,
      "source_file": "contracts/local-dev-runbook.md",
      "source_location": null,
      "weight": 1.0,
      "_src": "flow_local_run_sequence",
      "_tgt": "port_8002_s3_storage",
      "source": "flow_local_run_sequence",
      "target": "port_8002_s3_storage"
    },
    {
      "relation": "starts",
      "confidence": "EXTRACTED",
      "confidence_score": 1.0,
      "source_file": "contracts/local-dev-runbook.md",
      "source_location": null,
      "weight": 1.0,
      "_src": "flow_local_run_sequence",
      "_tgt": "port_8001_bim_control",
      "source": "flow_local_run_sequence",
      "target": "port_8001_bim_control"
    },
    {
      "relation": "starts",
      "confidence": "EXTRACTED",
      "confidence_score": 1.0,
      "source_file": "contracts/local-dev-runbook.md",
      "source_location": null,
      "weight": 1.0,
      "_src": "flow_local_run_sequence",
      "_tgt": "port_8003_conversion",
      "source": "flow_local_run_sequence",
      "target": "port_8003_conversion"
    },
    {
      "relation": "starts",
      "confidence": "EXTRACTED",
      "confidence_score": 1.0,
      "source_file": "contracts/local-dev-runbook.md",
      "source_location": null,
      "weight": 1.0,
      "_src": "flow_local_run_sequence",
      "_tgt": "port_8004_coordinator",
      "source": "flow_local_run_sequence",
      "target": "port_8004_coordinator"
    },
    {
      "relation": "starts",
      "confidence": "EXTRACTED",
      "confidence_score": 1.0,
      "source_file": "contracts/local-dev-runbook.md",
      "source_location": null,
      "weight": 1.0,
      "_src": "flow_local_run_sequence",
      "_tgt": "port_49100_webrtc",
      "source": "flow_local_run_sequence",
      "target": "port_49100_webrtc"
    },
    {
      "relation": "starts",
      "confidence": "EXTRACTED",
      "confidence_score": 1.0,
      "source_file": "contracts/local-dev-runbook.md",
      "source_location": null,
      "weight": 1.0,
      "_src": "flow_local_run_sequence",
      "_tgt": "port_5173_web_viewer",
      "source": "flow_local_run_sequence",
      "target": "port_5173_web_viewer"
    },
    {
      "relation": "conceptually_related_to",
      "confidence": "EXTRACTED",
      "confidence_score": 1.0,
      "source_file": "plans/BIM_REVIEW_COORDINATOR_WEB_VIEWER_EXECUTION_PLAN.md",
      "source_location": null,
      "weight": 1.0,
      "_src": "risk_conversion_not_ready",
      "_tgt": "rule_missing_usdc_gate",
      "source": "rule_missing_usdc_gate",
      "target": "risk_conversion_not_ready"
    },
    {
      "relation": "conceptually_related_to",
      "confidence": "EXTRACTED",
      "confidence_score": 1.0,
      "source_file": "plans/BIM_REVIEW_COORDINATOR_WEB_VIEWER_EXECUTION_PLAN.md",
      "source_location": "section 17.4",
      "weight": 1.0,
      "_src": "risk_webrtc_down",
      "_tgt": "port_49100_webrtc",
      "source": "risk_webrtc_down",
      "target": "port_49100_webrtc"
    }
  ],
  "hyperedges": [
    {
      "id": "conversion_artifact_closed_loop",
      "label": "Conversion Artifact Closed Loop",
      "nodes": [
        "service_conversion_service",
        "service_s3_storage",
        "service_bim_control",
        "service_review_coordinator",
        "service_web_viewer",
        "service_bim_streaming_server"
      ],
      "relation": "participate_in",
      "confidence": "INFERRED",
      "confidence_score": 0.9,
      "source_file": "plans/IFC_TO_USDC_CONVERSION_API_IMPLEMENTATION_PLAN.md"
    },
    {
      "id": "review_highlight_runtime_loop",
      "label": "Review Issue to 3D Runtime Loop",
      "nodes": [
        "data_review_issue",
        "data_element_mapping",
        "data_usd_prim_path",
        "dc_highlight_prims_request",
        "service_bim_streaming_server",
        "socket_highlight_request"
      ],
      "relation": "form",
      "confidence": "INFERRED",
      "confidence_score": 0.88,
      "source_file": "plans/BIM_REVIEW_COORDINATOR_WEB_VIEWER_EXECUTION_PLAN.md"
    },
    {
      "id": "single_repo_operational_context",
      "label": "Single Repo Operational Context",
      "nodes": [
        "repo_ai_bim_governance",
        "doc_nested_repo_remote_record",
        "doc_local_runbook",
        "doc_ifc_usdc_plan",
        "doc_review_web_plan"
      ],
      "relation": "form",
      "confidence": "INFERRED",
      "confidence_score": 0.82,
      "source_file": "git/nested-repo-remotes.md"
    }
  ]
}